isjsonschemasubset/__init__.py
isjsonschemasubset-0.0.2.dist-info/LICENSE
isjsonschemasubset-0.0.2.dist-info/METADATA
isjsonschemasubset-0.0.2.dist-info/WHEEL
isjsonschemasubset-0.0.2.dist-info/top_level.txt
isjsonschemasubset-0.0.2.dist-info/RECORD
