Metadata-Version: 2.1
Name: isjsonschemasubset
Version: 0.0.2
Summary: Check one JSON schema is a subset of another
Author-email: Oliver Russell <ojhrussell@gmail.com>
Maintainer-email: Oliver Russell <ojhrussell@gmail.com>
License: MIT License
Project-URL: homepage, https://leontrolski.github.io/
Keywords: JSONSchema,pydantic
Classifier: Programming Language :: Python
Requires-Python: >=3.11
License-File: LICENSE
Requires-Dist: pydantic >=2.3.0
Provides-Extra: dev
Requires-Dist: pytest >=7.2.2 ; extra == 'dev'
Requires-Dist: autoflake >=2.0.2 ; extra == 'dev'
Requires-Dist: black >=23.1.0 ; extra == 'dev'
Requires-Dist: mypy ; extra == 'dev'
